<annotation>
	<folder>image5</folder>
	<filename>IMG_20200302_144359.jpg</filename>
	<path>D:\Uni_Stuttgart\MA\image5\IMG_20200302_144359.jpg</path>
	<source>
		<database>Unknown</database>
	</source>
	<size>
		<width>806</width>
		<height>603</height>
		<depth>3</depth>
	</size>
	<segmented>0</segmented>
	<object>
		<name>white+white+silver</name>
		<pose>Unspecified</pose>
		<truncated>0</truncated>
		<difficult>0</difficult>
		<bndbox>
			<xmin>67</xmin>
			<ymin>164</ymin>
			<xmax>521</xmax>
			<ymax>430</ymax>
		</bndbox>
	</object>
	<object>
		<name>black+black+red</name>
		<pose>Unspecified</pose>
		<truncated>1</truncated>
		<difficult>0</difficult>
		<bndbox>
			<xmin>433</xmin>
			<ymin>50</ymin>
			<xmax>806</xmax>
			<ymax>461</ymax>
		</bndbox>
	</object>
</annotation>
