<annotation>
	<folder>resizedImage</folder>
	<filename>IMG_20200224_141658_0.jpg</filename>
	<path>D:\Uni_Stuttgart\MA\resizedImage\IMG_20200224_141658.jpg</path>
	<source>
		<database>Unknown</database>
	</source>
	<size>
		<width>452</width>
		<height>605</height>
		<depth>3</depth>
	</size>
	<segmented>0</segmented>
	<object>
		<name>white+black+red</name>
		<pose>Unspecified</pose>
		<truncated>0</truncated>
		<difficult>0</difficult>
		<bndbox>
			<xmin>62</xmin>
			<ymin>69</ymin>
			<xmax>106</xmax>
			<ymax>149</ymax>
		</bndbox>
	</object>
	<object>
		<name>black+white+silver</name>
		<pose>Unspecified</pose>
		<truncated>0</truncated>
		<difficult>0</difficult>
		<bndbox>
			<xmin>27</xmin>
			<ymin>31</ymin>
			<xmax>63</xmax>
			<ymax>93</ymax>
		</bndbox>
	</object>
</annotation>