<annotation>
	<folder>resizedImage</folder>
	<filename>IMG_20200224_141115_0.jpg</filename>
	<path>D:\Uni_Stuttgart\MA\resizedImage\IMG_20200224_141115.jpg</path>
	<source>
		<database>Unknown</database>
	</source>
	<size>
		<width>452</width>
		<height>605</height>
		<depth>3</depth>
	</size>
	<segmented>0</segmented>
	<object>
		<name>black+black+silver</name>
		<pose>Unspecified</pose>
		<truncated>0</truncated>
		<difficult>0</difficult>
		<bndbox>
			<xmin>157</xmin>
			<ymin>237</ymin>
			<xmax>342</xmax>
			<ymax>491</ymax>
		</bndbox>
	</object>
	<object>
		<name>white+white+red</name>
		<pose>Unspecified</pose>
		<truncated>0</truncated>
		<difficult>0</difficult>
		<bndbox>
			<xmin>293</xmin>
			<ymin>433</ymin>
			<xmax>514</xmax>
			<ymax>740</ymax>
		</bndbox>
	</object>
</annotation>