<annotation>
	<folder>image5</folder>
	<filename>IMG_20200302_142257_0.jpg</filename>
	<path>D:\Uni_Stuttgart\MA\image5\IMG_20200302_142257.jpg</path>
	<source>
		<database>Unknown</database>
	</source>
	<size>
		<width>806</width>
		<height>603</height>
		<depth>3</depth>
	</size>
	<segmented>0</segmented>
	<object>
		<name>black+white+red</name>
		<pose>Unspecified</pose>
		<truncated>0</truncated>
		<difficult>0</difficult>
		<bndbox>
			<xmin>43</xmin>
			<ymin>69</ymin>
			<xmax>118</xmax>
			<ymax>119</ymax>
		</bndbox>
	</object>
	<object>
		<name>white+black+silver</name>
		<pose>Unspecified</pose>
		<truncated>0</truncated>
		<difficult>0</difficult>
		<bndbox>
			<xmin>107</xmin>
			<ymin>72</ymin>
			<xmax>190</xmax>
			<ymax>120</ymax>
		</bndbox>
	</object>
</annotation>