<annotation>
	<folder>resizedImage</folder>
	<filename>IMG_20200224_141725_2.jpg</filename>
	<path>D:\Uni_Stuttgart\MA\resizedImage\IMG_20200224_141725.jpg</path>
	<source>
		<database>Unknown</database>
	</source>
	<size>
		<width>605</width>
		<height>452</height>
		<depth>3</depth>
	</size>
	<segmented>0</segmented>
	<object>
		<name>black+white+silver</name>
		<pose>Unspecified</pose>
		<truncated>0</truncated>
		<difficult>0</difficult>
		<bndbox>
			<xmin>24</xmin>
			<ymin>199</ymin>
			<xmax>265</xmax>
			<ymax>340</ymax>
		</bndbox>
	</object>
	<object>
		<name>white+black+red</name>
		<pose>Unspecified</pose>
		<truncated>0</truncated>
		<difficult>0</difficult>
		<bndbox>
			<xmin>309</xmin>
			<ymin>208</ymin>
			<xmax>546</xmax>
			<ymax>351</ymax>
		</bndbox>
	</object>
</annotation>